encrypteddict/__init__.py
encrypteddict-1.0.0.dist-info/LICENSE
encrypteddict-1.0.0.dist-info/METADATA
encrypteddict-1.0.0.dist-info/WHEEL
encrypteddict-1.0.0.dist-info/top_level.txt
encrypteddict-1.0.0.dist-info/RECORD
